oscillo/__init__.py
oscillo/app.py
oscillo/table.py
oscillo/worker.py
oscillo-1.0.0.dist-info/LICENSE.txt
oscillo-1.0.0.dist-info/METADATA
oscillo-1.0.0.dist-info/RECORD
oscillo-1.0.0.dist-info/WHEEL
oscillo-1.0.0.dist-info/entry_points.txt
oscillo-1.0.0.dist-info/top_level.txt
