Metadata-Version: 2.1
Name: oscillo
Version: 1.0.0
Summary: Record the system load at the execution of the command line and display it graphically
Home-page: https://github.com/raomuyang/cmd-oscillo
Author: Rao Mengnan
Author-email: raomengnan@gmail.com
Maintainer: Rao Mengnan
Maintainer-email: raomengnan@gmail.com
License: UNKNOWN
Platform: Independent
Classifier: Environment :: Console
Classifier: License :: OSI Approved :: Apache Software License
Classifier: Intended Audience :: Customer Service
Classifier: Intended Audience :: End Users/Desktop
Classifier: Operating System :: OS Independent
Classifier: Programming Language :: Python
Requires-Dist: psutil (>=5.2.2)
Requires-Dist: numpy (>=1.13.1)
Requires-Dist: PyYAML (==3.13)
Requires-Dist: terminaltables (==3.1.0)
Requires-Dist: futures (==3.2.0)
Requires-Dist: matplotlib
